mkdocs_schema_reader/__init__.py
mkdocs_schema_reader/schema_reader.py
mkdocs_schema_reader-0.11.1.dist-info/METADATA
mkdocs_schema_reader-0.11.1.dist-info/WHEEL
mkdocs_schema_reader-0.11.1.dist-info/entry_points.txt
mkdocs_schema_reader-0.11.1.dist-info/top_level.txt
mkdocs_schema_reader-0.11.1.dist-info/RECORD
