Metadata-Version: 2.1
Name: mkdocs-schema-reader
Version: 0.11.1
Summary: A MkDocs plugin to collate json schema files and convert them into markdown files
Home-page: https://github.com/magicaljellybeans/mkdocs_schema_reader
Author: Tom Robinson
Author-email: tome.robin@gmail.com
License: MIT
Keywords: mkdocs,schema,json,plugin
Platform: UNKNOWN
Requires-Python: >=3.6
Requires-Dist: mkdocs (>=1.0.4)
Requires-Dist: jsonschema2md
